trulioo_sdk/__init__.py
trulioo_sdk/api_client.py
trulioo_sdk/configuration.py
trulioo_sdk/exceptions.py
trulioo_sdk/model_utils.py
trulioo_sdk/rest.py
trulioo_sdk/api/__init__.py
trulioo_sdk/api/business_api.py
trulioo_sdk/api/configuration_api.py
trulioo_sdk/api/connection_api.py
trulioo_sdk/api/verifications_api.py
trulioo_sdk/apis/__init__.py
trulioo_sdk/model/__init__.py
trulioo_sdk/model/address.py
trulioo_sdk/model/appended_field.py
trulioo_sdk/model/business.py
trulioo_sdk/model/business_record.py
trulioo_sdk/model/business_registration_number.py
trulioo_sdk/model/business_registration_number_mask.py
trulioo_sdk/model/business_result.py
trulioo_sdk/model/business_search_request.py
trulioo_sdk/model/business_search_request_business_search_model.py
trulioo_sdk/model/business_search_response.py
trulioo_sdk/model/business_search_response_industry_code.py
trulioo_sdk/model/communication.py
trulioo_sdk/model/consent.py
trulioo_sdk/model/country_subdivision.py
trulioo_sdk/model/data_field.py
trulioo_sdk/model/data_fields.py
trulioo_sdk/model/datasource_field.py
trulioo_sdk/model/datasource_result.py
trulioo_sdk/model/document.py
trulioo_sdk/model/driver_licence.py
trulioo_sdk/model/location.py
trulioo_sdk/model/location_additional_fields.py
trulioo_sdk/model/national_id.py
trulioo_sdk/model/normalized_datasource_field.py
trulioo_sdk/model/normalized_datasource_group_country.py
trulioo_sdk/model/passport.py
trulioo_sdk/model/person_info.py
trulioo_sdk/model/person_info_additional_fields.py
trulioo_sdk/model/record.py
trulioo_sdk/model/record_rule.py
trulioo_sdk/model/result.py
trulioo_sdk/model/service_error.py
trulioo_sdk/model/test_entity_data_fields.py
trulioo_sdk/model/transaction_record_result.py
trulioo_sdk/model/transaction_record_result_all_of.py
trulioo_sdk/model/transaction_status.py
trulioo_sdk/model/verify_request.py
trulioo_sdk/model/verify_result.py
trulioo_sdk/models/__init__.py
trulioo_sdk-1.0.4.dist-info/METADATA
trulioo_sdk-1.0.4.dist-info/WHEEL
trulioo_sdk-1.0.4.dist-info/top_level.txt
trulioo_sdk-1.0.4.dist-info/RECORD
