Metadata-Version: 2.1
Name: trulioo-sdk
Version: 1.0.4
Summary: Trulioo Python SDK
Home-page: https://github.com/Trulioo/sdk-python/
Author: Trulioo
Author-email: support@trulioo.com
License: Apache-2.0
Keywords: Trulioo Python SDK
Platform: UNKNOWN
Requires-Python: >=3.6
Requires-Dist: urllib3 (>=1.25.3)
Requires-Dist: python-dateutil
